slate/__init__.py
slate/__main__.py
slate/annotate.py
slate/config.py
slate/data.py
slate/view.py
slate_nlp-1.1.3.dist-info/LICENSE.txt
slate_nlp-1.1.3.dist-info/METADATA
slate_nlp-1.1.3.dist-info/WHEEL
slate_nlp-1.1.3.dist-info/entry_points.txt
slate_nlp-1.1.3.dist-info/top_level.txt
slate_nlp-1.1.3.dist-info/RECORD
