Metadata-Version: 2.1
Name: slate-nlp
Version: 1.1.3
Summary: A terminal-based text annotation tool
Author-email: "Jonathan K. Kummerfeld" <jonathan.kummerfeld@sydney.edu.au>
License: Copyright (c) 2016-2023 Jonathan K Kummerfeld <jonathan.kummerfeld@sydney.edu.au>
Project-URL: Homepage, https://jkk.name/slate/
Project-URL: Bug Tracker, https://github.com/jkkummerfeld/slate/issues
Keywords: nlp,annotation,labeling,natural-language-processing,text-annotation
Classifier: Development Status :: 4 - Beta
Classifier: Programming Language :: Python :: 3
Classifier: Programming Language :: Python :: 2.6
Classifier: Programming Language :: Python :: 2.7
Classifier: License :: OSI Approved :: ISC License (ISCL)
Classifier: Operating System :: OS Independent
Classifier: Topic :: Scientific/Engineering :: Artificial Intelligence
Requires-Python: !=3.0.*,!=3.1.*,!=3.2.*,<4,>=2.6
License-File: LICENSE.txt
